{
  "$schema": "https://mintlify.com/docs.json",
  "name": "WiCAN Firmware",
  "theme": "palm",
  "colors": {
    "primary": "#4055b5",
    "light": "#9cacdc"
  },
  "favicon": "https://media.brand.dev/ce0b5528-90e8-4891-b615-1922395c8037.png",
  "navbar": {
    "primary": {
      "type": "github",
      "href": "https://github.com/meatpiHQ/wican-fw"
    }
  },
  "footer": {
    "socials": {
      "github": "https://github.com/meatpiHQ/wican-fw"
    }
  },
  "navigation": {
    "tabs": [
      {
        "tab": "Documentation",
        "groups": [
          {
            "group": "Get Started",
            "pages": [
              "introduction",
              "quickstart",
              "hardware-overview",
              "firmware-update"
            ]
          },
          {
            "group": "Configuration",
            "pages": [
              "config/wifi",
              "config/can",
              "config/sleep-mode",
              "config/factory-reset"
            ]
          },
          {
            "group": "Automate & OBD",
            "pages": [
              "config/automate/usage",
              "config/automate/supported-vehicles",
              "config/automate/vehicle-profiles",
              "config/automate/supported-parameters"
            ]
          },
          {
            "group": "Connectivity & Security",
            "pages": [
              "config/mqtt",
              "config/https",
              "config/vpn-wireguard",
              "config/abrp"
            ]
          }
        ]
      },
      {
        "tab": "Integrations",
        "groups": [
          {
            "group": "Home Assistant",
            "pages": [
              "home-assistant/overview",
              "home-assistant/integration-setup",
              "home-assistant/mqtt"
            ]
          },
          {
            "group": "CAN Tools",
            "pages": [
              "integrations/socketcan",
              "integrations/savvycan",
              "integrations/busmaster",
              "integrations/realdash",
              "integrations/car-scanner"
            ]
          },
          {
            "group": "API Reference",
            "pages": [
              "api/mqtt-api",
              "api/http-api",
              "api/expression-syntax"
            ]
          }
        ]
      }
    ]
  }
}
